[
  {
    "name": "random",
    "solutions": [
      {
        "config": {},
        "result": {
          "fitness": -7279.0,
          "duration": 2.8133392333984375e-05
        }
      }
    ]
  },
  {
    "name": "cbc",
    "solutions": [
      {
        "config": {},
        "result": {
          "fitness": -8056.0,
          "duration": 12.091713190078735
        }
      }
    ]
  },
  {
    "name": "glpk",
    "solutions": [
      {
        "config": {},
        "result": {
          "fitness": -7529.0,
          "duration": 8.182530641555786
        }
      }
    ]
  },
  {
    "name": "genetic#1",
    "solutions": [
      {
        "config": {},
        "result": {
          "fitness": -7062.0,
          "duration": 3.0234971046447754
        }
      }
    ]
  },
  {
    "name": "genetic#2",
    "solutions": [
      {
        "config": {},
        "result": {
          "fitness": -6829.0,
          "duration": 0.3999052047729492
        }
      }
    ]
  },
  {
    "name": "genetic#3",
    "solutions": [
      {
        "config": {},
        "result": {
          "fitness": -6864.0,
          "duration": 3.2072126865386963
        }
      }
    ]
  }
]