[
  {
    "name": "random",
    "solutions": [
      {
        "config": {},
        "result": {
          "fitness": -15435.0,
          "duration": 2.4080276489257812e-05
        }
      }
    ]
  },
  {
    "name": "single_point genetic",
    "solutions": [
      {
        "config": {},
        "result": {
          "fitness": -14014.0,
          "duration": 0.5525197982788086
        }
      }
    ]
  },
  {
    "name": "two_points genetic",
    "solutions": [
      {
        "config": {},
        "result": {
          "fitness": -14156.0,
          "duration": 0.5419540405273438
        }
      }
    ]
  },
  {
    "name": "uniform genetic",
    "solutions": [
      {
        "config": {},
        "result": {
          "fitness": -13970.0,
          "duration": 0.5077028274536133
        }
      }
    ]
  },
  {
    "name": "glpk",
    "solutions": [
      {
        "config": {},
        "result": {
          "fitness": -14675.0,
          "duration": 59.692495822906494
        }
      }
    ]
  },
  {
    "name": "cbc",
    "solutions": [
      {
        "config": {},
        "result": {
          "fitness": -14319.0,
          "duration": 26.199777841567993
        }
      }
    ]
  },
  {
    "name": "mpec_minlp",
    "solutions": [
      {
        "config": {},
        "result": {
          "fitness": -14675.0,
          "duration": 60.739733934402466
        }
      }
    ]
  }
]