[
  {
    "name": "random",
    "solutions": [
      {
        "config": {},
        "result": {
          "fitness": -4433.0,
          "duration": 2.193450927734375e-05
        }
      }
    ]
  },
  {
    "name": "single_point genetic",
    "solutions": [
      {
        "config": {},
        "result": {
          "fitness": -4225.0,
          "duration": 0.2960691452026367
        }
      }
    ]
  },
  {
    "name": "two_points genetic",
    "solutions": [
      {
        "config": {},
        "result": {
          "fitness": -4225.0,
          "duration": 0.29901885986328125
        }
      }
    ]
  },
  {
    "name": "uniform genetic",
    "solutions": [
      {
        "config": {},
        "result": {
          "fitness": -4225.0,
          "duration": 0.29367971420288086
        }
      }
    ]
  },
  {
    "name": "glpk",
    "solutions": [
      {
        "config": {},
        "result": {
          "fitness": -4433.0,
          "duration": 2.9044041633605957
        }
      }
    ]
  },
  {
    "name": "cbc",
    "solutions": [
      {
        "config": {},
        "result": {
          "fitness": -4225.0,
          "duration": 2.748270034790039
        }
      }
    ]
  },
  {
    "name": "mpec_minlp",
    "solutions": [
      {
        "config": {},
        "result": {
          "fitness": -4433.0,
          "duration": 2.228933095932007
        }
      }
    ]
  }
]