[
  {
    "name": "random",
    "solutions": [
      {
        "config": {},
        "result": {
          "fitness": -4815.0,
          "duration": 3.0994415283203125e-05
        }
      }
    ]
  },
  {
    "name": "cbc",
    "solutions": [
      {
        "config": {},
        "result": {
          "fitness": -4072.0,
          "duration": 3.4567887783050537
        }
      }
    ]
  },
  {
    "name": "glpk",
    "solutions": [
      {
        "config": {},
        "result": {
          "fitness": -4247.0,
          "duration": 5.67909574508667
        }
      }
    ]
  },
  {
    "name": "genetic#1",
    "solutions": [
      {
        "config": {},
        "result": {
          "fitness": -3723.0,
          "duration": 2.5723822116851807
        }
      }
    ]
  },
  {
    "name": "genetic#2",
    "solutions": [
      {
        "config": {},
        "result": {
          "fitness": -3582.0,
          "duration": 0.26900506019592285
        }
      }
    ]
  },
  {
    "name": "genetic#3",
    "solutions": [
      {
        "config": {},
        "result": {
          "fitness": -3355.0,
          "duration": 1.7611017227172852
        }
      }
    ]
  }
]