[
  {
    "name": "glpk",
    "solutions": [
      {
        "config": {
          "k": 2
        },
        "result": {
          "fitness": 0.00510204081632653,
          "duration": 0.05221199989318848
        }
      }
    ]
  },
  {
    "name": "xpress",
    "solutions": [
      {
        "config": {
          "k": 2
        },
        "result": {
          "fitness": 0.00510204081632653,
          "duration": 0.047943115234375
        }
      }
    ]
  },
  {
    "name": "mpec_minlp",
    "solutions": [
      {
        "config": {
          "k": 2
        },
        "result": {
          "fitness": 0.00510204081632653,
          "duration": 0.08320999145507812
        }
      }
    ]
  },
  {
    "name": "ilogcp",
    "solutions": [
      {
        "config": {
          "k": 2
        },
        "result": {
          "fitness": 0.00510204081632653,
          "duration": 0.1093597412109375
        }
      }
    ]
  },
  {
    "name": "binary_genetic",
    "solutions": [
      {
        "config": {
          "k": 2,
          "num_generations": 100,
          "sol_per_pop": 4,
          "num_parents_mating": 2,
          "parent_selection_type": "sss",
          "keep_parents": 1,
          "crossover_type": "scattered",
          "mutation_type": "scramble",
          "mutation_percent_genes": 10
        },
        "result": {
          "fitness": 0.0,
          "duration": 0.21560215950012207
        }
      }
    ]
  },
  {
    "name": "discrete_genetic",
    "solutions": [
      {
        "config": {
          "k": 2,
          "num_generations": 100,
          "sol_per_pop": 4,
          "num_parents_mating": 2,
          "parent_selection_type": "sss",
          "keep_parents": 1,
          "crossover_type": "scattered",
          "mutation_type": "scramble",
          "mutation_percent_genes": 10
        },
        "result": {
          "fitness": 0.00510204081632653,
          "duration": 0.843998908996582
        }
      }
    ]
  },
  {
    "name": "binary_rl_A2C",
    "solutions": [
      {
        "config": {
          "k": 2,
          "total_timesteps": 100
        },
        "result": {
          "fitness": 0.0,
          "duration": 0.30036211013793945
        }
      }
    ]
  },
  {
    "name": "binary_rl_PPO",
    "solutions": [
      {
        "config": {
          "k": 2,
          "total_timesteps": 100
        },
        "result": {
          "fitness": 0.0,
          "duration": 2.9534037113189697
        }
      }
    ]
  },
  {
    "name": "discrete_rl_A2C",
    "solutions": [
      {
        "config": {
          "k": 2,
          "total_timesteps": 100
        },
        "result": {
          "fitness": 0.00510204081632653,
          "duration": 1.8679370880126953
        }
      }
    ]
  },
  {
    "name": "discrete_rl_PPO",
    "solutions": [
      {
        "config": {
          "k": 2,
          "total_timesteps": 100
        },
        "result": {
          "fitness": 0.00510204081632653,
          "duration": 32.17069482803345
        }
      }
    ]
  }
]