[
  {
    "name": "random",
    "solutions": [
      {
        "config": {},
        "result": {
          "fitness": -6459.0,
          "duration": 4.38690185546875e-05
        }
      }
    ]
  },
  {
    "name": "cbc",
    "solutions": [
      {
        "config": {},
        "result": {
          "fitness": -5550.0,
          "duration": 5.7061989307403564
        }
      }
    ]
  },
  {
    "name": "glpk",
    "solutions": [
      {
        "config": {},
        "result": {
          "fitness": -6335.0,
          "duration": 10.985711097717285
        }
      }
    ]
  },
  {
    "name": "genetic#1",
    "solutions": [
      {
        "config": {},
        "result": {
          "fitness": -5532.0,
          "duration": 2.3232760429382324
        }
      }
    ]
  },
  {
    "name": "genetic#2",
    "solutions": [
      {
        "config": {},
        "result": {
          "fitness": -5640.0,
          "duration": 0.365739107131958
        }
      }
    ]
  },
  {
    "name": "genetic#3",
    "solutions": [
      {
        "config": {},
        "result": {
          "fitness": -5555.0,
          "duration": 2.4470810890197754
        }
      }
    ]
  }
]