[
  {
    "name": "glpk",
    "solutions": [
      {
        "config": {
          "k": 2
        },
        "result": {
          "fitness": 0.0034602076124567475,
          "duration": 0.0740506649017334
        }
      }
    ]
  },
  {
    "name": "xpress",
    "solutions": [
      {
        "config": {
          "k": 2
        },
        "result": {
          "fitness": 0.0034602076124567475,
          "duration": 0.0749959945678711
        }
      }
    ]
  },
  {
    "name": "mpec_minlp",
    "solutions": [
      {
        "config": {
          "k": 2
        },
        "result": {
          "fitness": 0.0034602076124567475,
          "duration": 0.10010004043579102
        }
      }
    ]
  },
  {
    "name": "ilogcp",
    "solutions": [
      {
        "config": {
          "k": 2
        },
        "result": {
          "fitness": 0.0034602076124567475,
          "duration": 0.1191551685333252
        }
      }
    ]
  },
  {
    "name": "binary_genetic",
    "solutions": [
      {
        "config": {
          "k": 2,
          "num_generations": 100,
          "sol_per_pop": 4,
          "num_parents_mating": 2,
          "parent_selection_type": "sss",
          "keep_parents": 1,
          "crossover_type": "scattered",
          "mutation_type": "scramble",
          "mutation_percent_genes": 10
        },
        "result": {
          "fitness": 0.0,
          "duration": 0.3162569999694824
        }
      }
    ]
  },
  {
    "name": "discrete_genetic",
    "solutions": [
      {
        "config": {
          "k": 2,
          "num_generations": 100,
          "sol_per_pop": 4,
          "num_parents_mating": 2,
          "parent_selection_type": "sss",
          "keep_parents": 1,
          "crossover_type": "scattered",
          "mutation_type": "scramble",
          "mutation_percent_genes": 10
        },
        "result": {
          "fitness": 0.0034602076124567475,
          "duration": 2.3187170028686523
        }
      }
    ]
  },
  {
    "name": "binary_rl_A2C",
    "solutions": [
      {
        "config": {
          "k": 2,
          "total_timesteps": 100
        },
        "result": {
          "fitness": 0.0,
          "duration": 0.32136011123657227
        }
      }
    ]
  },
  {
    "name": "binary_rl_PPO",
    "solutions": [
      {
        "config": {
          "k": 2,
          "total_timesteps": 100
        },
        "result": {
          "fitness": 0.0,
          "duration": 3.5076217651367188
        }
      }
    ]
  },
  {
    "name": "discrete_rl_A2C",
    "solutions": [
      {
        "config": {
          "k": 2,
          "total_timesteps": 100
        },
        "result": {
          "fitness": 0.0034602076124567475,
          "duration": 3.2139599323272705
        }
      }
    ]
  },
  {
    "name": "discrete_rl_PPO",
    "solutions": [
      {
        "config": {
          "k": 2,
          "total_timesteps": 100
        },
        "result": {
          "fitness": 0.0034602076124567475,
          "duration": 61.08292508125305
        }
      }
    ]
  }
]