[
  {
    "name": "random",
    "solutions": [
      {
        "config": {},
        "result": {
          "fitness": -4554.0,
          "duration": 2.002716064453125e-05
        }
      }
    ]
  },
  {
    "name": "single_point genetic",
    "solutions": [
      {
        "config": {},
        "result": {
          "fitness": -4554.0,
          "duration": 0.1350111961364746
        }
      }
    ]
  },
  {
    "name": "two_points genetic",
    "solutions": [
      {
        "config": {},
        "result": {
          "fitness": -4554.0,
          "duration": 0.23065614700317383
        }
      }
    ]
  },
  {
    "name": "uniform genetic",
    "solutions": [
      {
        "config": {},
        "result": {
          "fitness": -4130.0,
          "duration": 0.21813297271728516
        }
      }
    ]
  },
  {
    "name": "glpk",
    "solutions": [
      {
        "config": {},
        "result": {
          "fitness": -4212.0,
          "duration": 0.34246087074279785
        }
      }
    ]
  },
  {
    "name": "cbc",
    "solutions": [
      {
        "config": {},
        "result": {
          "fitness": -4266.0,
          "duration": 0.6173667907714844
        }
      }
    ]
  },
  {
    "name": "mpec_minlp",
    "solutions": [
      {
        "config": {},
        "result": {
          "fitness": -4212.0,
          "duration": 0.3872189521789551
        }
      }
    ]
  }
]