[
  {
    "name": "random",
    "solutions": [
      {
        "config": {},
        "result": {
          "fitness": -25590.0,
          "duration": 2.5033950805664062e-05
        }
      }
    ]
  },
  {
    "name": "single_point genetic",
    "solutions": [
      {
        "config": {},
        "result": {
          "fitness": -23297.0,
          "duration": 0.5533590316772461
        }
      }
    ]
  },
  {
    "name": "two_points genetic",
    "solutions": [
      {
        "config": {},
        "result": {
          "fitness": -23313.0,
          "duration": 0.5447440147399902
        }
      }
    ]
  },
  {
    "name": "uniform genetic",
    "solutions": [
      {
        "config": {},
        "result": {
          "fitness": -23089.0,
          "duration": 0.5756278038024902
        }
      }
    ]
  },
  {
    "name": "glpk",
    "solutions": [
      {
        "config": {},
        "result": {
          "fitness": -23427.0,
          "duration": 64.73747563362122
        }
      }
    ]
  },
  {
    "name": "cbc",
    "solutions": [
      {
        "config": {},
        "result": {
          "fitness": -23070.0,
          "duration": 36.212636947631836
        }
      }
    ]
  },
  {
    "name": "mpec_minlp",
    "solutions": [
      {
        "config": {},
        "result": {
          "fitness": -23427.0,
          "duration": 66.42189311981201
        }
      }
    ]
  }
]