[
  {
    "name": "random",
    "solutions": [
      {
        "config": {},
        "result": {
          "fitness": -19687.0,
          "duration": 3.0040740966796875e-05
        }
      }
    ]
  },
  {
    "name": "single_point genetic",
    "solutions": [
      {
        "config": {},
        "result": {
          "fitness": -18761.0,
          "duration": 0.6312050819396973
        }
      }
    ]
  },
  {
    "name": "two_points genetic",
    "solutions": [
      {
        "config": {},
        "result": {
          "fitness": -18301.0,
          "duration": 0.5483901500701904
        }
      }
    ]
  },
  {
    "name": "uniform genetic",
    "solutions": [
      {
        "config": {},
        "result": {
          "fitness": -18240.0,
          "duration": 0.44414186477661133
        }
      }
    ]
  },
  {
    "name": "glpk",
    "solutions": [
      {
        "config": {},
        "result": {
          "fitness": -18875.0,
          "duration": 17.43089509010315
        }
      }
    ]
  },
  {
    "name": "cbc",
    "solutions": [
      {
        "config": {},
        "result": {
          "fitness": -19321.0,
          "duration": 18.826855182647705
        }
      }
    ]
  },
  {
    "name": "mpec_minlp",
    "solutions": [
      {
        "config": {},
        "result": {
          "fitness": -18875.0,
          "duration": 15.93163275718689
        }
      }
    ]
  }
]