[
  {
    "name": "random",
    "solutions": [
      {
        "config": {},
        "result": {
          "fitness": -12950.0,
          "duration": 2.193450927734375e-05
        }
      }
    ]
  },
  {
    "name": "cbc",
    "solutions": [
      {
        "config": {},
        "result": {
          "fitness": -12755.0,
          "duration": 25.847864151000977
        }
      }
    ]
  },
  {
    "name": "glpk",
    "solutions": [
      {
        "config": {},
        "result": {
          "fitness": -12969.0,
          "duration": 34.74922323226929
        }
      }
    ]
  },
  {
    "name": "genetic#1",
    "solutions": [
      {
        "config": {},
        "result": {
          "fitness": -11340.0,
          "duration": 2.4707210063934326
        }
      }
    ]
  },
  {
    "name": "genetic#2",
    "solutions": [
      {
        "config": {},
        "result": {
          "fitness": -11420.0,
          "duration": 0.47554492950439453
        }
      }
    ]
  },
  {
    "name": "genetic#3",
    "solutions": [
      {
        "config": {},
        "result": {
          "fitness": -11573.0,
          "duration": 3.6325480937957764
        }
      }
    ]
  }
]