[
  {
    "name": "random",
    "solutions": [
      {
        "config": {},
        "result": {
          "fitness": -1334.0,
          "duration": 3.0994415283203125e-05
        }
      }
    ]
  },
  {
    "name": "cbc",
    "solutions": [
      {
        "config": {},
        "result": {
          "fitness": -1151.0,
          "duration": 1.0932080745697021
        }
      }
    ]
  },
  {
    "name": "glpk",
    "solutions": [
      {
        "config": {},
        "result": {
          "fitness": -1566.0,
          "duration": 0.8062238693237305
        }
      }
    ]
  },
  {
    "name": "genetic#1",
    "solutions": [
      {
        "config": {},
        "result": {
          "fitness": -1379.0,
          "duration": 1.543323278427124
        }
      }
    ]
  },
  {
    "name": "genetic#2",
    "solutions": [
      {
        "config": {},
        "result": {
          "fitness": -1274.0,
          "duration": 0.3185081481933594
        }
      }
    ]
  },
  {
    "name": "genetic#3",
    "solutions": [
      {
        "config": {},
        "result": {
          "fitness": -1233.0,
          "duration": 1.6763238906860352
        }
      }
    ]
  }
]